odoo/addons/sale_warn_option/README.rst
odoo/addons/sale_warn_option/__init__.py
odoo/addons/sale_warn_option/__manifest__.py
odoo/addons/sale_warn_option/i18n/es.po
odoo/addons/sale_warn_option/i18n/sale_warn_option.pot
odoo/addons/sale_warn_option/models/__init__.py
odoo/addons/sale_warn_option/models/product_template.py
odoo/addons/sale_warn_option/models/res_partner.py
odoo/addons/sale_warn_option/models/warn_option.py
odoo/addons/sale_warn_option/readme/CONTEXT.md
odoo/addons/sale_warn_option/readme/CONTRIBUTORS.md
odoo/addons/sale_warn_option/readme/DESCRIPTION.md
odoo/addons/sale_warn_option/readme/USAGE.md
odoo/addons/sale_warn_option/static/description/icon.png
odoo/addons/sale_warn_option/static/description/index.html
odoo/addons/sale_warn_option/tests/__init__.py
odoo/addons/sale_warn_option/tests/test_warn_options.py
odoo/addons/sale_warn_option/views/product_template_views.xml
odoo/addons/sale_warn_option/views/res_partner_views.xml
odoo_addon_sale_warn_option-15.0.1.0.1.dist-info/METADATA
odoo_addon_sale_warn_option-15.0.1.0.1.dist-info/WHEEL
odoo_addon_sale_warn_option-15.0.1.0.1.dist-info/top_level.txt
odoo_addon_sale_warn_option-15.0.1.0.1.dist-info/RECORD
